<?xml version="1.0" encoding="utf-8"?><index><!-- saved from url=(0016)http://localhost -->
<stem n="transit"><phr n="Transitions"><ent r="143" t="16" w="440" /><ent r="143" t="16" w="440" /><ent r="1000" t="23" w="2" /><ent r="1000" t="23" w="2" /><ent r="92" t="23" w="6" /><ent r="92" t="23" w="6" /><ent r="4" t="23" w="19" /><ent r="4" t="23" w="19" /><ent r="3" t="23" w="26" /><ent r="3" t="23" w="26" /><ent r="5" t="48" w="375" /><ent r="5" t="48" w="375" /><ent r="71" t="70" w="1031" /><ent r="71" t="70" w="1031" /><ent r="6" t="122" w="249" /><ent r="6" t="122" w="249" /><ent r="4" t="210" w="17" /><ent r="4" t="210" w="17" /><ent r="3" t="210" w="24" /><ent r="3" t="210" w="24" /><ent r="100" t="210" w="124" /><ent r="100" t="210" w="124" /><ent r="6" t="210" w="212" /><ent r="6" t="210" w="212" /><ent r="7" t="210" w="304" /><ent r="7" t="210" w="304" /><ent r="6" t="210" w="309" /><ent r="6" t="210" w="309" /><ent r="7" t="210" w="503" /><ent r="7" t="210" w="503" /><ent r="6" t="210" w="508" /><ent r="6" t="210" w="508" /><ent r="6" t="210" w="1208" /><ent r="6" t="210" w="1208" /><ent r="4" t="210" w="1304" /><ent r="4" t="210" w="1304" /><ent r="10" t="323" w="365" /><ent r="7" t="329" w="937" /><ent r="7" t="329" w="937" /><ent r="7" t="332" w="246" /><ent r="7" t="332" w="246" /></phr><phr n="transition"><ent r="3" t="23" w="35" /><ent r="3" t="23" w="35" /><ent r="3" t="23" w="111" /><ent r="6" t="38" w="501" /><ent r="6" t="38" w="551" /><ent r="6" t="38" w="551" /><ent r="3" t="57" w="24" /><ent r="3" t="57" w="24" /><ent r="6" t="57" w="86" /><ent r="6" t="57" w="86" /><ent r="8" t="57" w="221" /><ent r="8" t="57" w="221" /><ent r="5" t="72" w="107" /><ent r="5" t="72" w="107" /><ent r="5" t="72" w="122" /><ent r="5" t="72" w="122" /><ent r="3" t="86" w="118" /><ent r="3" t="86" w="118" /><ent r="6" t="86" w="380" /><ent r="6" t="86" w="380" /><ent r="67" t="110" w="161" /><ent r="9" t="121" w="257" /><ent r="9" t="121" w="257" /><ent r="6" t="122" w="109" /><ent r="6" t="122" w="109" /><ent r="83" t="122" w="180" /><ent r="83" t="122" w="180" /><ent r="6" t="122" w="202" /><ent r="6" t="122" w="202" /><ent r="6" t="122" w="213" /><ent r="6" t="122" w="223" /><ent r="6" t="122" w="223" /><ent r="6" t="122" w="246" /><ent r="6" t="122" w="246" /><ent r="6" t="122" w="262" /><ent r="6" t="122" w="262" /><ent r="7" t="132" w="675" /><ent r="7" t="132" w="675" /><ent r="7" t="132" w="700" /><ent r="7" t="132" w="700" /><ent r="6" t="133" w="200" /><ent r="6" t="133" w="414" /><ent r="6" t="133" w="414" /><ent r="6" t="133" w="439" /><ent r="6" t="133" w="439" /><ent r="83" t="134" w="775" /><ent r="83" t="134" w="775" /><ent r="4" t="134" w="851" /><ent r="4" t="134" w="851" /><ent r="4" t="134" w="894" /><ent r="100" t="136" w="916" /><ent r="100" t="136" w="916" /><ent r="83" t="136" w="922" /><ent r="83" t="136" w="922" /><ent r="4" t="136" w="928" /><ent r="4" t="136" w="928" /><ent r="4" t="136" w="943" /><ent r="4" t="136" w="945" /><ent r="4" t="136" w="945" /><ent r="4" t="136" w="954" /><ent r="6" t="136" w="966" /><ent r="6" t="136" w="993" /><ent r="6" t="136" w="1020" /><ent r="6" t="136" w="1020" /><ent r="4" t="180" w="406" /><ent r="4" t="180" w="406" /><ent r="4" t="180" w="430" /><ent r="4" t="180" w="430" /><ent r="4" t="190" w="305" /><ent r="6" t="191" w="573" /><ent r="6" t="191" w="573" /><ent r="143" t="195" w="302" /><ent r="143" t="195" w="302" /><ent r="3" t="210" w="33" /><ent r="3" t="210" w="33" /><ent r="3" t="210" w="109" /><ent r="6" t="210" w="266" /><ent r="6" t="210" w="314" /><ent r="6" t="210" w="314" /><ent r="6" t="210" w="344" /><ent r="6" t="210" w="384" /><ent r="6" t="210" w="384" /><ent r="6" t="210" w="434" /><ent r="6" t="210" w="434" /><ent r="6" t="210" w="446" /><ent r="83" t="210" w="452" /><ent r="83" t="210" w="452" /><ent r="4" t="210" w="476" /><ent r="4" t="210" w="476" /><ent r="6" t="210" w="491" /><ent r="6" t="210" w="513" /><ent r="6" t="210" w="513" /><ent r="6" t="210" w="543" /><ent r="6" t="210" w="575" /><ent r="6" t="210" w="575" /><ent r="6" t="210" w="618" /><ent r="6" t="210" w="618" /><ent r="6" t="210" w="630" /><ent r="6" t="210" w="650" /><ent r="6" t="210" w="721" /><ent r="6" t="210" w="721" /><ent r="4" t="210" w="845" /><ent r="4" t="210" w="845" /><ent r="83" t="210" w="888" /><ent r="83" t="210" w="888" /><ent r="4" t="210" w="895" /><ent r="4" t="210" w="895" /><ent r="4" t="210" w="913" /><ent r="4" t="210" w="913" /><ent r="73" t="210" w="918" /><ent r="73" t="210" w="918" /><ent r="6" t="210" w="934" /><ent r="6" t="210" w="934" /><ent r="6" t="210" w="948" /><ent r="6" t="210" w="948" /><ent r="73" t="210" w="957" /><ent r="73" t="210" w="957" /><ent r="4" t="210" w="976" /><ent r="4" t="210" w="976" /><ent r="4" t="210" w="1010" /><ent r="4" t="210" w="1010" /><ent r="4" t="210" w="1034" /><ent r="4" t="210" w="1034" /><ent r="83" t="210" w="1044" /><ent r="83" t="210" w="1044" /><ent r="4" t="210" w="1050" /><ent r="4" t="210" w="1050" /><ent r="4" t="210" w="1065" /><ent r="4" t="210" w="1067" /><ent r="4" t="210" w="1067" /><ent r="4" t="210" w="1076" /><ent r="6" t="210" w="1089" /><ent r="6" t="210" w="1117" /><ent r="6" t="210" w="1144" /><ent r="6" t="210" w="1144" /><ent r="83" t="210" w="1157" /><ent r="83" t="210" w="1157" /><ent r="4" t="210" w="1169" /><ent r="4" t="210" w="1169" /><ent r="4" t="210" w="1173" /><ent r="83" t="210" w="1181" /><ent r="83" t="210" w="1181" /><ent r="6" t="210" w="1205" /><ent r="6" t="210" w="1205" /><ent r="83" t="210" w="1219" /><ent r="83" t="210" w="1219" /><ent r="6" t="210" w="1254" /><ent r="83" t="210" w="1266" /><ent r="83" t="210" w="1266" /><ent r="4" t="210" w="1282" /><ent r="4" t="210" w="1282" /><ent r="4" t="210" w="1297" /><ent r="4" t="210" w="1297" /><ent r="4" t="210" w="1301" /><ent r="4" t="210" w="1301" /><ent r="4" t="210" w="1335" /><ent r="4" t="210" w="1335" /><ent r="4" t="210" w="1357" /><ent r="4" t="210" w="1387" /><ent r="4" t="210" w="1387" /><ent r="83" t="210" w="1432" /><ent r="83" t="210" w="1432" /><ent r="6" t="210" w="1444" /><ent r="6" t="210" w="1458" /><ent r="6" t="210" w="1458" /><ent r="83" t="210" w="1504" /><ent r="83" t="210" w="1504" /><ent r="4" t="210" w="1535" /><ent r="3" t="263" w="181" /><ent r="3" t="263" w="181" /><ent r="65" t="269" w="100" /><ent r="67" t="291" w="173" /><ent r="7" t="310" w="735" /><ent r="7" t="310" w="735" /><ent r="7" t="329" w="915" /><ent r="7" t="329" w="915" /><ent r="7" t="329" w="930" /><ent r="7" t="329" w="930" /><ent r="7" t="329" w="934" /><ent r="7" t="329" w="934" /><ent r="7" t="329" w="966" /><ent r="7" t="329" w="966" /><ent r="7" t="329" w="992" /><ent r="7" t="332" w="661" /><ent r="7" t="332" w="661" /><ent r="8" t="332" w="1787" /><ent r="8" t="332" w="1787" /><ent r="8" t="332" w="1872" /><ent r="8" t="332" w="1872" /><ent r="7" t="332" w="2157" /><ent r="7" t="332" w="2157" /><ent r="7" t="332" w="2169" /><ent r="7" t="332" w="2169" /></phr><phr n="transitions"><ent r="3" t="23" w="69" /><ent r="3" t="23" w="69" /><ent r="66" t="23" w="186" /><ent r="66" t="23" w="186" /><ent r="143" t="35" w="227" /><ent r="143" t="35" w="227" /><ent r="4" t="41" w="302" /><ent r="4" t="41" w="302" /><ent r="5" t="48" w="367" /><ent r="5" t="48" w="367" /><ent r="68" t="48" w="392" /><ent r="68" t="48" w="392" /><ent r="3" t="68" w="32" /><ent r="6" t="81" w="277" /><ent r="6" t="81" w="277" /><ent r="6" t="81" w="284" /><ent r="6" t="81" w="296" /><ent r="6" t="81" w="710" /><ent r="6" t="81" w="710" /><ent r="6" t="81" w="1006" /><ent r="6" t="81" w="1006" /><ent r="6" t="86" w="368" /><ent r="6" t="86" w="368" /><ent r="6" t="122" w="236" /><ent r="69" t="122" w="241" /><ent r="69" t="122" w="241" /><ent r="100" t="134" w="769" /><ent r="100" t="134" w="769" /><ent r="4" t="136" w="962" /><ent r="67" t="180" w="450" /><ent r="67" t="180" w="450" /><ent r="4" t="182" w="700" /><ent r="3" t="195" w="91" /><ent r="3" t="195" w="108" /><ent r="3" t="195" w="108" /><ent r="1000" t="210" w="2" /><ent r="1000" t="210" w="2" /><ent r="92" t="210" w="5" /><ent r="92" t="210" w="5" /><ent r="3" t="210" w="67" /><ent r="3" t="210" w="67" /><ent r="100" t="210" w="128" /><ent r="100" t="210" w="128" /><ent r="100" t="210" w="131" /><ent r="100" t="210" w="131" /><ent r="100" t="210" w="134" /><ent r="100" t="210" w="134" /><ent r="83" t="210" w="290" /><ent r="83" t="210" w="290" /><ent r="6" t="210" w="414" /><ent r="6" t="210" w="414" /><ent r="4" t="210" w="465" /><ent r="4" t="210" w="465" /><ent r="6" t="210" w="579" /><ent r="6" t="210" w="579" /><ent r="6" t="210" w="598" /><ent r="6" t="210" w="598" /><ent r="73" t="210" w="640" /><ent r="73" t="210" w="640" /><ent r="6" t="210" w="652" /><ent r="6" t="210" w="652" /><ent r="6" t="210" w="677" /><ent r="6" t="210" w="677" /><ent r="6" t="210" w="701" /><ent r="6" t="210" w="701" /><ent r="6" t="210" w="741" /><ent r="6" t="210" w="741" /><ent r="6" t="210" w="777" /><ent r="6" t="210" w="777" /><ent r="6" t="210" w="817" /><ent r="6" t="210" w="817" /><ent r="4" t="210" w="852" /><ent r="4" t="210" w="1084" /><ent r="3" t="237" w="60" /><ent r="8" t="242" w="510" /><ent r="8" t="242" w="510" /><ent r="4" t="262" w="695" /><ent r="6" t="266" w="2015" /><ent r="3" t="270" w="90" /><ent r="9" t="277" w="432" /><ent r="9" t="277" w="432" /><ent r="9" t="277" w="529" /><ent r="9" t="277" w="529" /><ent r="4" t="292" w="1880" /><ent r="4" t="292" w="1880" /><ent r="7" t="322" w="1773" /><ent r="7" t="322" w="1773" /><ent r="7" t="329" w="577" /><ent r="7" t="329" w="577" /></phr><phr n="Transition"><ent r="7" t="122" w="193" /><ent r="7" t="122" w="193" /><ent r="7" t="136" w="981" /><ent r="7" t="136" w="981" /><ent r="3" t="191" w="114" /><ent r="3" t="191" w="114" /><ent r="7" t="210" w="419" /><ent r="7" t="210" w="419" /><ent r="7" t="210" w="603" /><ent r="7" t="210" w="603" /><ent r="100" t="210" w="1039" /><ent r="100" t="210" w="1039" /><ent r="7" t="210" w="1105" /><ent r="7" t="210" w="1105" /><ent r="5" t="210" w="1162" /><ent r="5" t="210" w="1162" /><ent r="7" t="210" w="1186" /><ent r="7" t="210" w="1186" /><ent r="7" t="210" w="1224" /><ent r="7" t="210" w="1224" /><ent r="5" t="210" w="1324" /><ent r="5" t="210" w="1324" /><ent r="8" t="329" w="957" /><ent r="8" t="329" w="957" /></phr></stem><stem n="fx"><phr n="FX"><ent r="143" t="16" w="443" /><ent r="143" t="16" w="443" /><ent r="1000" t="24" w="3" /><ent r="1000" t="24" w="3" /><ent r="100" t="24" w="13" /><ent r="100" t="24" w="13" /><ent r="92" t="24" w="18" /><ent r="92" t="24" w="18" /><ent r="4" t="24" w="32" /><ent r="4" t="24" w="32" /><ent r="3" t="24" w="41" /><ent r="3" t="24" w="41" /><ent r="3" t="27" w="116" /><ent r="143" t="32" w="95" /><ent r="143" t="32" w="112" /><ent r="143" t="32" w="112" /><ent r="143" t="32" w="115" /><ent r="7" t="61" w="116" /><ent r="7" t="61" w="116" /><ent r="6" t="61" w="166" /><ent r="6" t="61" w="166" /><ent r="6" t="61" w="220" /><ent r="6" t="61" w="220" /><ent r="7" t="62" w="145" /><ent r="7" t="62" w="145" /><ent r="7" t="62" w="174" /><ent r="7" t="62" w="174" /><ent r="7" t="62" w="325" /><ent r="7" t="62" w="325" /><ent r="7" t="62" w="378" /><ent r="7" t="62" w="378" /><ent r="6" t="64" w="232" /><ent r="6" t="64" w="232" /><ent r="6" t="64" w="258" /><ent r="6" t="64" w="258" /><ent r="6" t="64" w="310" /><ent r="6" t="64" w="310" /><ent r="6" t="65" w="240" /><ent r="6" t="65" w="240" /><ent r="71" t="70" w="1035" /><ent r="71" t="70" w="1035" /><ent r="5" t="72" w="138" /><ent r="5" t="72" w="138" /><ent r="56" t="90" w="1262" /><ent r="56" t="90" w="1262" /><ent r="100" t="90" w="1290" /><ent r="100" t="90" w="1290" /><ent r="5" t="90" w="1294" /><ent r="5" t="90" w="1294" /><ent r="9" t="90" w="1619" /><ent r="9" t="90" w="1619" /><ent r="3" t="137" w="117" /><ent r="3" t="137" w="117" /><ent r="6" t="137" w="256" /><ent r="6" t="137" w="256" /><ent r="6" t="137" w="694" /><ent r="6" t="137" w="694" /><ent r="4" t="137" w="812" /><ent r="4" t="137" w="812" /><ent r="4" t="137" w="975" /><ent r="4" t="137" w="975" /><ent r="6" t="137" w="1029" /><ent r="6" t="137" w="1029" /><ent r="6" t="137" w="1050" /><ent r="6" t="137" w="1050" /><ent r="6" t="137" w="1080" /><ent r="6" t="137" w="1080" /><ent r="5" t="137" w="1198" /><ent r="5" t="137" w="1198" /><ent r="4" t="137" w="1209" /><ent r="4" t="137" w="1209" /><ent r="6" t="137" w="1311" /><ent r="6" t="137" w="1311" /><ent r="7" t="137" w="1337" /><ent r="7" t="137" w="1337" /><ent r="6" t="137" w="1771" /><ent r="6" t="137" w="1771" /><ent r="6" t="137" w="1954" /><ent r="6" t="137" w="1954" /><ent r="6" t="137" w="2173" /><ent r="6" t="137" w="2173" /><ent r="6" t="137" w="2644" /><ent r="6" t="137" w="2644" /><ent r="6" t="137" w="2667" /><ent r="6" t="137" w="2667" /><ent r="6" t="138" w="128" /><ent r="6" t="138" w="128" /><ent r="6" t="138" w="145" /><ent r="6" t="138" w="145" /><ent r="5" t="138" w="177" /><ent r="5" t="138" w="177" /><ent r="4" t="138" w="363" /><ent r="4" t="138" w="363" /><ent r="3" t="138" w="373" /><ent r="3" t="138" w="373" /><ent r="67" t="164" w="773" /><ent r="67" t="164" w="773" /><ent r="3" t="179" w="65" /><ent r="3" t="179" w="65" /><ent r="100" t="179" w="616" /><ent r="100" t="179" w="616" /><ent r="5" t="179" w="623" /><ent r="5" t="179" w="623" /><ent r="7" t="179" w="2075" /><ent r="7" t="179" w="2075" /><ent r="7" t="179" w="2100" /><ent r="7" t="179" w="2100" /><ent r="7" t="179" w="2133" /><ent r="7" t="179" w="2133" /><ent r="7" t="179" w="2138" /><ent r="7" t="179" w="2138" /><ent r="6" t="179" w="2307" /><ent r="6" t="179" w="2307" /><ent r="6" t="179" w="2322" /><ent r="6" t="179" w="2322" /><ent r="100" t="180" w="777" /><ent r="100" t="180" w="777" /><ent r="5" t="180" w="784" /><ent r="5" t="180" w="784" /><ent r="66" t="181" w="123" /><ent r="66" t="181" w="123" /><ent r="5" t="181" w="184" /><ent r="5" t="181" w="184" /><ent r="4" t="181" w="229" /><ent r="4" t="181" w="229" /><ent r="5" t="181" w="257" /><ent r="5" t="181" w="257" /><ent r="5" t="182" w="1002" /><ent r="5" t="182" w="1002" /><ent r="4" t="182" w="1049" /><ent r="4" t="182" w="1049" /><ent r="5" t="182" w="1299" /><ent r="5" t="182" w="1299" /><ent r="11" t="184" w="224" /><ent r="11" t="184" w="224" /><ent r="6" t="187" w="1113" /><ent r="6" t="187" w="1113" /><ent r="6" t="187" w="1128" /><ent r="6" t="187" w="1128" /><ent r="5" t="187" w="1789" /><ent r="5" t="187" w="1789" /><ent r="7" t="189" w="113" /><ent r="7" t="189" w="113" /><ent r="7" t="189" w="120" /><ent r="7" t="189" w="120" /><ent r="6" t="189" w="126" /><ent r="6" t="189" w="126" /><ent r="7" t="189" w="139" /><ent r="7" t="189" w="139" /><ent r="6" t="189" w="211" /><ent r="6" t="189" w="211" /><ent r="6" t="189" w="362" /><ent r="6" t="189" w="362" /><ent r="6" t="189" w="380" /><ent r="6" t="189" w="380" /><ent r="5" t="189" w="593" /><ent r="5" t="189" w="593" /><ent r="7" t="189" w="623" /><ent r="7" t="189" w="623" /><ent r="7" t="189" w="677" /><ent r="7" t="189" w="677" /><ent r="7" t="189" w="697" /><ent r="7" t="189" w="697" /><ent r="7" t="189" w="704" /><ent r="7" t="189" w="704" /><ent r="6" t="189" w="710" /><ent r="6" t="189" w="710" /><ent r="7" t="189" w="723" /><ent r="7" t="189" w="723" /><ent r="6" t="189" w="795" /><ent r="6" t="189" w="795" /><ent r="6" t="189" w="828" /><ent r="6" t="189" w="828" /><ent r="6" t="189" w="847" /><ent r="6" t="189" w="847" /><ent r="3" t="191" w="107" /><ent r="3" t="191" w="127" /><ent r="3" t="191" w="127" /><ent r="6" t="191" w="474" /><ent r="6" t="191" w="474" /><ent r="4" t="191" w="717" /><ent r="4" t="191" w="717" /><ent r="4" t="191" w="780" /><ent r="4" t="191" w="780" /><ent r="5" t="192" w="118" /><ent r="5" t="192" w="118" /><ent r="5" t="192" w="173" /><ent r="5" t="192" w="173" /><ent r="5" t="192" w="217" /><ent r="5" t="192" w="217" /><ent r="7" t="196" w="253" /><ent r="7" t="196" w="253" /><ent r="7" t="196" w="277" /><ent r="7" t="196" w="277" /><ent r="6" t="196" w="307" /><ent r="6" t="196" w="307" /><ent r="6" t="196" w="407" /><ent r="6" t="196" w="407" /><ent r="6" t="196" w="418" /><ent r="6" t="196" w="418" /><ent r="7" t="196" w="491" /><ent r="7" t="196" w="491" /><ent r="7" t="196" w="530" /><ent r="7" t="196" w="530" /><ent r="6" t="196" w="542" /><ent r="6" t="196" w="542" /><ent r="5" t="196" w="691" /><ent r="5" t="196" w="691" /><ent r="4" t="196" w="702" /><ent r="4" t="196" w="702" /><ent r="7" t="196" w="715" /><ent r="7" t="196" w="715" /><ent r="7" t="196" w="769" /><ent r="7" t="196" w="769" /><ent r="4" t="196" w="805" /><ent r="4" t="196" w="805" /><ent r="7" t="197" w="160" /><ent r="7" t="197" w="160" /><ent r="7" t="197" w="183" /><ent r="7" t="197" w="183" /><ent r="6" t="197" w="213" /><ent r="6" t="197" w="213" /><ent r="6" t="197" w="313" /><ent r="6" t="197" w="313" /><ent r="6" t="197" w="324" /><ent r="6" t="197" w="324" /><ent r="7" t="197" w="351" /><ent r="7" t="197" w="351" /><ent r="6" t="197" w="365" /><ent r="6" t="197" w="365" /><ent r="4" t="197" w="452" /><ent r="4" t="197" w="452" /><ent r="100" t="198" w="128" /><ent r="100" t="198" w="128" /><ent r="6" t="198" w="137" /><ent r="6" t="198" w="137" /><ent r="6" t="198" w="213" /><ent r="6" t="198" w="213" /><ent r="7" t="198" w="379" /><ent r="7" t="198" w="379" /><ent r="6" t="198" w="415" /><ent r="6" t="198" w="415" /><ent r="6" t="198" w="459" /><ent r="6" t="198" w="459" /><ent r="7" t="198" w="523" /><ent r="7" t="198" w="523" /><ent r="6" t="198" w="542" /><ent r="6" t="198" w="542" /><ent r="6" t="198" w="555" /><ent r="6" t="198" w="555" /><ent r="4" t="198" w="588" /><ent r="4" t="198" w="588" /><ent r="5" t="198" w="703" /><ent r="5" t="198" w="703" /><ent r="4" t="198" w="713" /><ent r="4" t="198" w="713" /><ent r="7" t="198" w="726" /><ent r="7" t="198" w="726" /><ent r="7" t="198" w="780" /><ent r="7" t="198" w="780" /><ent r="4" t="198" w="817" /><ent r="4" t="198" w="817" /><ent r="6" t="199" w="160" /><ent r="6" t="199" w="160" /><ent r="5" t="199" w="257" /><ent r="5" t="199" w="257" /><ent r="5" t="199" w="301" /><ent r="5" t="199" w="301" /><ent r="4" t="201" w="55" /><ent r="4" t="201" w="55" /><ent r="4" t="201" w="63" /><ent r="4" t="201" w="63" /><ent r="7" t="201" w="227" /><ent r="7" t="201" w="227" /><ent r="6" t="201" w="347" /><ent r="6" t="201" w="347" /><ent r="5" t="201" w="389" /><ent r="5" t="201" w="389" /><ent r="5" t="201" w="422" /><ent r="5" t="201" w="422" /><ent r="7" t="201" w="452" /><ent r="7" t="201" w="452" /><ent r="6" t="201" w="479" /><ent r="6" t="201" w="479" /><ent r="6" t="201" w="487" /><ent r="6" t="201" w="487" /><ent r="4" t="201" w="529" /><ent r="4" t="201" w="529" /><ent r="67" t="201" w="551" /><ent r="67" t="201" w="551" /><ent r="67" t="201" w="667" /><ent r="67" t="201" w="667" /><ent r="4" t="201" w="801" /><ent r="4" t="201" w="801" /><ent r="68" t="202" w="200" /><ent r="68" t="202" w="200" /><ent r="8" t="202" w="252" /><ent r="8" t="202" w="252" /><ent r="8" t="202" w="267" /><ent r="8" t="202" w="267" /><ent r="8" t="202" w="294" /><ent r="8" t="202" w="294" /><ent r="8" t="202" w="299" /><ent r="8" t="202" w="299" /><ent r="100" t="203" w="13" /><ent r="100" t="203" w="13" /><ent r="3" t="204" w="109" /><ent r="3" t="204" w="109" /><ent r="1000" t="205" w="1" /><ent r="1000" t="205" w="1" /><ent r="100" t="205" w="16" /><ent r="100" t="205" w="16" /><ent r="92" t="205" w="46" /><ent r="92" t="205" w="46" /><ent r="3" t="205" w="61" /><ent r="3" t="205" w="61" /><ent r="4" t="205" w="82" /><ent r="4" t="205" w="82" /><ent r="4" t="205" w="157" /><ent r="4" t="205" w="157" /><ent r="4" t="205" w="183" /><ent r="4" t="205" w="183" /><ent r="5" t="205" w="190" /><ent r="5" t="205" w="190" /><ent r="3" t="206" w="38" /><ent r="3" t="206" w="38" /><ent r="83" t="206" w="78" /><ent r="83" t="206" w="78" /><ent r="6" t="206" w="96" /><ent r="6" t="206" w="96" /><ent r="57" t="206" w="99" /><ent r="57" t="206" w="102" /><ent r="57" t="206" w="102" /><ent r="83" t="206" w="152" /><ent r="83" t="206" w="152" /><ent r="6" t="206" w="168" /><ent r="6" t="206" w="168" /><ent r="57" t="206" w="171" /><ent r="57" t="206" w="174" /><ent r="57" t="206" w="174" /><ent r="4" t="207" w="27" /><ent r="4" t="207" w="27" /><ent r="4" t="207" w="83" /><ent r="4" t="207" w="83" /><ent r="54" t="208" w="31" /><ent r="54" t="208" w="31" /><ent r="54" t="208" w="65" /><ent r="54" t="208" w="65" /><ent r="5" t="208" w="1021" /><ent r="5" t="208" w="1021" /><ent r="7" t="208" w="1042" /><ent r="7" t="208" w="1042" /><ent r="7" t="208" w="1096" /><ent r="7" t="208" w="1096" /><ent r="6" t="209" w="94" /><ent r="6" t="209" w="94" /><ent r="6" t="209" w="107" /><ent r="6" t="209" w="107" /><ent r="69" t="209" w="127" /><ent r="69" t="209" w="127" /><ent r="6" t="209" w="152" /><ent r="6" t="209" w="152" /><ent r="6" t="209" w="194" /><ent r="6" t="209" w="194" /><ent r="7" t="209" w="223" /><ent r="7" t="209" w="223" /><ent r="6" t="209" w="261" /><ent r="6" t="209" w="261" /><ent r="6" t="209" w="315" /><ent r="6" t="209" w="315" /><ent r="6" t="209" w="326" /><ent r="6" t="209" w="326" /><ent r="9" t="209" w="372" /><ent r="9" t="209" w="372" /><ent r="72" t="209" w="389" /><ent r="72" t="209" w="389" /><ent r="9" t="209" w="403" /><ent r="9" t="209" w="403" /><ent r="7" t="209" w="436" /><ent r="7" t="209" w="436" /><ent r="6" t="209" w="483" /><ent r="6" t="209" w="483" /><ent r="6" t="209" w="532" /><ent r="6" t="209" w="532" /><ent r="6" t="209" w="543" /><ent r="6" t="209" w="543" /><ent r="9" t="209" w="589" /><ent r="9" t="209" w="589" /><ent r="72" t="209" w="608" /><ent r="72" t="209" w="608" /><ent r="9" t="209" w="622" /><ent r="9" t="209" w="622" /><ent r="7" t="209" w="680" /><ent r="7" t="209" w="680" /><ent r="6" t="209" w="724" /><ent r="6" t="209" w="724" /><ent r="6" t="209" w="772" /><ent r="6" t="209" w="772" /><ent r="6" t="209" w="782" /><ent r="6" t="209" w="782" /><ent r="7" t="209" w="853" /><ent r="7" t="209" w="853" /><ent r="7" t="209" w="888" /><ent r="7" t="209" w="888" /><ent r="6" t="209" w="938" /><ent r="6" t="209" w="938" /><ent r="6" t="209" w="987" /><ent r="6" t="209" w="987" /><ent r="6" t="209" w="998" /><ent r="6" t="209" w="998" /><ent r="9" t="209" w="1044" /><ent r="9" t="209" w="1044" /><ent r="72" t="209" w="1060" /><ent r="72" t="209" w="1060" /><ent r="9" t="209" w="1096" /><ent r="9" t="209" w="1096" /><ent r="9" t="209" w="1114" /><ent r="9" t="209" w="1114" /><ent r="9" t="209" w="1138" /><ent r="9" t="209" w="1138" /><ent r="9" t="209" w="1151" /><ent r="9" t="209" w="1151" /><ent r="4" t="209" w="1349" /><ent r="4" t="209" w="1349" /><ent r="4" t="209" w="1464" /><ent r="4" t="209" w="1464" /><ent r="4" t="209" w="1551" /><ent r="4" t="209" w="1551" /><ent r="6" t="210" w="200" /><ent r="6" t="210" w="200" /><ent r="6" t="210" w="278" /><ent r="6" t="210" w="278" /><ent r="6" t="210" w="404" /><ent r="6" t="210" w="404" /><ent r="6" t="210" w="588" /><ent r="6" t="210" w="588" /><ent r="6" t="210" w="1199" /><ent r="6" t="210" w="1199" /><ent r="6" t="210" w="1214" /><ent r="6" t="210" w="1214" /><ent r="6" t="210" w="1237" /><ent r="6" t="210" w="1237" /><ent r="4" t="210" w="1548" /><ent r="4" t="210" w="1548" /><ent r="5" t="214" w="50" /><ent r="5" t="214" w="50" /><ent r="100" t="215" w="350" /><ent r="100" t="215" w="350" /><ent r="9" t="215" w="354" /><ent r="9" t="215" w="354" /><ent r="8" t="215" w="372" /><ent r="8" t="215" w="372" /><ent r="8" t="215" w="423" /><ent r="8" t="215" w="423" /><ent r="9" t="215" w="661" /><ent r="9" t="215" w="661" /><ent r="9" t="215" w="666" /><ent r="9" t="215" w="666" /><ent r="143" t="216" w="159" /><ent r="143" t="216" w="159" /><ent r="4" t="224" w="141" /><ent r="4" t="224" w="141" /><ent r="4" t="224" w="167" /><ent r="4" t="224" w="167" /><ent r="5" t="224" w="174" /><ent r="5" t="224" w="174" /><ent r="7" t="224" w="219" /><ent r="7" t="224" w="219" /><ent r="8" t="224" w="232" /><ent r="8" t="224" w="232" /><ent r="4" t="224" w="2194" /><ent r="4" t="224" w="2194" /><ent r="7" t="225" w="236" /><ent r="7" t="225" w="236" /><ent r="6" t="225" w="243" /><ent r="6" t="225" w="243" /><ent r="12" t="229" w="279" /><ent r="12" t="229" w="279" /><ent r="11" t="229" w="286" /><ent r="11" t="229" w="286" /><ent r="12" t="229" w="418" /><ent r="12" t="229" w="418" /><ent r="11" t="229" w="427" /><ent r="11" t="229" w="427" /><ent r="8" t="229" w="660" /><ent r="8" t="229" w="660" /><ent r="7" t="229" w="665" /><ent r="7" t="229" w="665" /><ent r="7" t="229" w="684" /><ent r="7" t="229" w="684" /><ent r="7" t="229" w="690" /><ent r="7" t="229" w="690" /><ent r="8" t="231" w="198" /><ent r="8" t="231" w="198" /><ent r="8" t="231" w="260" /><ent r="8" t="231" w="260" /><ent r="3" t="232" w="170" /><ent r="3" t="232" w="170" /><ent r="143" t="233" w="60" /><ent r="143" t="233" w="60" /><ent r="1000" t="234" w="4" /><ent r="92" t="234" w="15" /><ent r="7" t="234" w="90" /><ent r="7" t="234" w="90" /><ent r="6" t="234" w="95" /><ent r="6" t="234" w="95" /><ent r="69" t="234" w="116" /><ent r="69" t="234" w="116" /><ent r="6" t="234" w="128" /><ent r="6" t="234" w="128" /><ent r="6" t="234" w="134" /><ent r="6" t="234" w="134" /><ent r="4" t="235" w="184" /><ent r="4" t="235" w="184" /><ent r="4" t="235" w="209" /><ent r="4" t="235" w="209" /><ent r="5" t="235" w="216" /><ent r="5" t="235" w="216" /><ent r="4" t="235" w="255" /><ent r="4" t="235" w="255" /><ent r="5" t="235" w="267" /><ent r="5" t="235" w="267" /><ent r="4" t="236" w="127" /><ent r="4" t="236" w="127" /><ent r="4" t="236" w="152" /><ent r="4" t="236" w="152" /><ent r="5" t="236" w="159" /><ent r="5" t="236" w="159" /><ent r="4" t="236" w="202" /><ent r="4" t="236" w="202" /><ent r="5" t="236" w="214" /><ent r="5" t="236" w="214" /><ent r="5" t="236" w="2060" /><ent r="5" t="236" w="2060" /><ent r="5" t="236" w="2086" /><ent r="5" t="236" w="2086" /><ent r="4" t="236" w="2096" /><ent r="4" t="236" w="2096" /><ent r="5" t="236" w="2113" /><ent r="5" t="236" w="2113" /><ent r="4" t="236" w="2116" /><ent r="4" t="236" w="2116" /><ent r="5" t="236" w="2132" /><ent r="5" t="236" w="2132" /><ent r="4" t="236" w="2135" /><ent r="4" t="236" w="2135" /><ent r="7" t="236" w="2218" /><ent r="7" t="236" w="2218" /><ent r="7" t="236" w="2248" /><ent r="7" t="236" w="2248" /><ent r="7" t="236" w="2278" /><ent r="7" t="236" w="2278" /><ent r="7" t="236" w="2308" /><ent r="7" t="236" w="2308" /><ent r="3" t="252" w="260" /><ent r="3" t="252" w="260" /><ent r="5" t="262" w="536" /><ent r="5" t="262" w="536" /><ent r="7" t="263" w="271" /><ent r="7" t="263" w="271" /><ent r="8" t="306" w="3148" /><ent r="8" t="306" w="3148" /><ent r="8" t="306" w="3151" /><ent r="8" t="306" w="4072" /><ent r="8" t="306" w="4072" /><ent r="8" t="310" w="629" /><ent r="8" t="310" w="629" /><ent r="8" t="310" w="860" /><ent r="8" t="310" w="860" /><ent r="6" t="313" w="1056" /><ent r="6" t="313" w="1056" /><ent r="100" t="322" w="50" /><ent r="100" t="322" w="50" /><ent r="100" t="322" w="1817" /><ent r="100" t="322" w="1817" /><ent r="8" t="322" w="1824" /><ent r="8" t="322" w="1824" /><ent r="8" t="322" w="1847" /><ent r="8" t="322" w="1847" /><ent r="10" t="323" w="367" /><ent r="7" t="332" w="260" /><ent r="7" t="332" w="260" /><ent r="8" t="332" w="613" /><ent r="8" t="332" w="613" /><ent r="7" t="332" w="3602" /><ent r="7" t="332" w="3602" /></phr></stem></index>